_qualpal.cpython-312-aarch64-linux-musl.so
include/qualpal/analyze.h
include/qualpal/color_difference.h
include/qualpal/colors.h
include/qualpal/matrix.h
include/qualpal/metrics.h
include/qualpal/qualpal.h
include/qualpal/threads.h
lib/libqualpal.a
lib/cmake/qualpal/qualpal-config-version.cmake
lib/cmake/qualpal/qualpal-config.cmake
lib/cmake/qualpal/qualpal-targets-release.cmake
lib/cmake/qualpal/qualpal-targets.cmake
qualpal/__init__.py
qualpal/color.py
qualpal/palette.py
qualpal/py.typed
qualpal/qualpal.py
qualpal/utils.py
qualpal.libs/libgcc_s-2d945d6c.so.1
qualpal.libs/libgomp-1ede7ee7.so.1.0.0
qualpal.libs/libstdc++-85f2cd6d.so.6.0.33
share/doc/qualpal/LICENSE
qualpal-1.1.0.dist-info/METADATA
qualpal-1.1.0.dist-info/WHEEL
qualpal-1.1.0.dist-info/RECORD
qualpal-1.1.0.dist-info/licenses/LICENSE
qualpal-1.1.0.dist-info/sboms/auditwheel.cdx.json
