Metadata-Version: 2.4
Name: qualpal
Version: 1.1.0
Summary: Automatically generate qualitative color palettes with distinct colors
Keywords: color,palette,qualitative,visualization,data-science
Author-Email: Johan Larsson <johan@jolars.co>
Maintainer-Email: Johan Larsson <johan@jolars.co>
License-Expression: MIT
License-File: LICENSE
Classifier: Development Status :: 4 - Beta
Classifier: Intended Audience :: Science/Research
Classifier: Intended Audience :: Developers
Classifier: Topic :: Scientific/Engineering :: Visualization
Classifier: Operating System :: MacOS
Classifier: Operating System :: Microsoft :: Windows
Classifier: Operating System :: POSIX :: Linux
Classifier: Operating System :: POSIX
Classifier: Operating System :: Unix
Classifier: Programming Language :: C++
Classifier: Programming Language :: Python :: 3 :: Only
Classifier: Programming Language :: Python :: 3.9
Classifier: Programming Language :: Python :: 3.10
Classifier: Programming Language :: Python :: 3.11
Classifier: Programming Language :: Python :: 3.12
Classifier: Programming Language :: Python :: 3.13
Classifier: Programming Language :: Python :: 3.14
Project-URL: homepage, https://github.com/jolars/qualpal-py
Project-URL: repository, https://github.com/jolars/qualpal-py
Project-URL: documentation, https://jolars.github.io/qualpal-py/
Project-URL: changelog, https://github.com/jolars/qualpal-py/blob/main/CHANGELOG.md
Project-URL: tracker, https://github.com/jolars/qualpal-py/issues
Requires-Python: >=3.9
Provides-Extra: viz
Requires-Dist: matplotlib>=3.5; extra == "viz"
